cipher_tools/__init__.py
cipher_tools/cipher_tools.py
cipher_tools-0.0.3.dist-info/LICENSE
cipher_tools-0.0.3.dist-info/WHEEL
cipher_tools-0.0.3.dist-info/METADATA
cipher_tools-0.0.3.dist-info/RECORD
