Metadata-Version: 2.1
Name: cipher-tools
Version: 0.0.3
Summary: A python library to assist in the creation of ciphers
Home-page: https://gitlab.com/mokytis/cipher-tools
License: MIT
Author: Luke Spademan
Author-email: info@lukespademan.com
Requires-Python: >=3.8,<4.0
Classifier: License :: OSI Approved :: MIT License
Classifier: Programming Language :: Python :: 3
Classifier: Programming Language :: Python :: 3.8
Project-URL: Repository, https://gitlab.com/mokytis/cipher-tools
